fx_lab/__init__.py
fx_lab/replay.py
fx_lab-0.0.0.dist-info/LICENSE
fx_lab-0.0.0.dist-info/METADATA
fx_lab-0.0.0.dist-info/WHEEL
fx_lab-0.0.0.dist-info/top_level.txt
fx_lab-0.0.0.dist-info/RECORD
