Metadata-Version: 2.1
Name: fx-lab
Version: 0.0.0
Summary: Test framework for audio fx and instruments
Home-page: https://github.com/jonastallhage/fx-lab
Author: Jonas Tallhage
Author-email: jonas@tallhage.se
License: UNKNOWN
Project-URL: Bug Tracker, https://github.com/jonastallhage/fx-lab/issues
Platform: UNKNOWN
Classifier: Programming Language :: Python :: 3
Classifier: License :: OSI Approved :: GNU General Public License v3 (GPLv3)
Classifier: Operating System :: OS Independent
Requires-Python: >=3.7.1
License-File: LICENSE
